pastiche/__init__.py
pastiche/__main__.py
pastiche/pastiche.py
pastiche/version.txt
pastiche/vgg19.py
pastiche/vgg19_weights_tf_dim_ordering_tf_kernels_notop_q.bin
pastiche-1.6.0.dist-info/LICENSE
pastiche-1.6.0.dist-info/METADATA
pastiche-1.6.0.dist-info/WHEEL
pastiche-1.6.0.dist-info/entry_points.txt
pastiche-1.6.0.dist-info/top_level.txt
pastiche-1.6.0.dist-info/RECORD
