Metadata-Version: 2.1
Name: pastiche
Version: 1.6.0
Summary: A PyTorch implementation of Neural Style Transfer (NST)
Home-page: https://github.com/dstein64/pastiche
Author: Daniel Steinberg
Author-email: ds@dannyadam.com
License: MIT
Keywords: gatys,style-transfer,neural-style-transfer
Classifier: Development Status :: 4 - Beta
Classifier: Intended Audience :: Developers
Classifier: Intended Audience :: Science/Research
Classifier: Topic :: Scientific/Engineering
Classifier: Topic :: Artistic Software
Classifier: License :: OSI Approved :: MIT License
Classifier: Operating System :: Unix
Classifier: Operating System :: POSIX :: Linux
Classifier: Operating System :: MacOS
Classifier: Operating System :: Microsoft :: Windows
Classifier: Programming Language :: Python :: 3
Requires-Python: >=3.6
License-File: LICENSE
Requires-Dist: pillow
Requires-Dist: torch
Provides-Extra: dev
Requires-Dist: h5py ; extra == 'dev'
Requires-Dist: kmeans1d ; extra == 'dev'
